odoo/addons/account_statement_import_sheet_file/README.rst
odoo/addons/account_statement_import_sheet_file/__init__.py
odoo/addons/account_statement_import_sheet_file/__manifest__.py
odoo/addons/account_statement_import_sheet_file/data/map_data.xml
odoo/addons/account_statement_import_sheet_file/i18n/account_statement_import_sheet_file.pot
odoo/addons/account_statement_import_sheet_file/i18n/es.po
odoo/addons/account_statement_import_sheet_file/i18n/es_AR.po
odoo/addons/account_statement_import_sheet_file/i18n/it.po
odoo/addons/account_statement_import_sheet_file/i18n/nl.po
odoo/addons/account_statement_import_sheet_file/i18n/pt.po
odoo/addons/account_statement_import_sheet_file/i18n/tr.po
odoo/addons/account_statement_import_sheet_file/i18n/zh_CN.po
odoo/addons/account_statement_import_sheet_file/models/__init__.py
odoo/addons/account_statement_import_sheet_file/models/account_journal.py
odoo/addons/account_statement_import_sheet_file/models/account_statement_import.py
odoo/addons/account_statement_import_sheet_file/models/account_statement_import_sheet_mapping.py
odoo/addons/account_statement_import_sheet_file/models/account_statement_import_sheet_parser.py
odoo/addons/account_statement_import_sheet_file/readme/CONFIGURE.md
odoo/addons/account_statement_import_sheet_file/readme/CONTRIBUTORS.md
odoo/addons/account_statement_import_sheet_file/readme/DESCRIPTION.md
odoo/addons/account_statement_import_sheet_file/readme/HISTORY.md
odoo/addons/account_statement_import_sheet_file/readme/USAGE.md
odoo/addons/account_statement_import_sheet_file/security/ir.model.access.csv
odoo/addons/account_statement_import_sheet_file/static/description/icon.png
odoo/addons/account_statement_import_sheet_file/static/description/index.html
odoo/addons/account_statement_import_sheet_file/tests/__init__.py
odoo/addons/account_statement_import_sheet_file/tests/test_account_statement_import_sheet_file.py
odoo/addons/account_statement_import_sheet_file/tests/fixtures/balance.csv
odoo_addon_account_statement_import_sheet_file-18.0.1.0.0.3.dist-info/METADATA
odoo_addon_account_statement_import_sheet_file-18.0.1.0.0.3.dist-info/WHEEL
odoo_addon_account_statement_import_sheet_file-18.0.1.0.0.3.dist-info/top_level.txt
odoo_addon_account_statement_import_sheet_file-18.0.1.0.0.3.dist-info/RECORD
